rda_solver/__init__.py
rda_solver/main.py
rda_solver4win-1.0.2.dist-info/METADATA
rda_solver4win-1.0.2.dist-info/WHEEL
rda_solver4win-1.0.2.dist-info/top_level.txt
rda_solver4win-1.0.2.dist-info/RECORD
