Metadata-Version: 2.1
Name: rda_solver4win
Version: 1.0.2
Summary: A light weight command line menu that supports Windows, MacOS, and Linux
Author: Ruihua Han
Author-email: 
Keywords: python,menu,rda,windows,mac,linux
Classifier: Development Status :: 1 - Planning
Classifier: Intended Audience :: Developers
Classifier: Programming Language :: Python :: 3
Classifier: Operating System :: Unix
Classifier: Operating System :: MacOS :: MacOS X
Classifier: Operating System :: Microsoft :: Windows
Requires-Dist: getch; platform_system == "MacOS"
Requires-Dist: getch; platform_system == "Unix"
